README.md
setup.py
CryptoGu_main.egg-info/PKG-INFO
CryptoGu_main.egg-info/SOURCES.txt
CryptoGu_main.egg-info/dependency_links.txt
CryptoGu_main.egg-info/requires.txt
CryptoGu_main.egg-info/top_level.txt
Topapp/CryptoGu-main.py